enacrestic/__init__.py
enacrestic/app.py
enacrestic/conf.py
enacrestic/const.py
enacrestic/logger.py
enacrestic/main.py
enacrestic/restic_backup.py
enacrestic/state.py
enacrestic/utils.py
enacrestic/pixmaps/backup_in_pause.png
enacrestic/pixmaps/backup_in_pause_badge.png
enacrestic/pixmaps/backup_in_progress.png
enacrestic/pixmaps/backup_success.png
enacrestic/pixmaps/backup_success_badge.png
enacrestic/pixmaps/error.png
enacrestic/pixmaps/error_badge.png
enacrestic/pixmaps/forget_in_progress.png
enacrestic/pixmaps/just_launched.png
enacrestic/pixmaps/just_launched_badge.png
enacrestic/pixmaps/no_network.png
enacrestic/pixmaps/no_network_badge.png
enacrestic/pixmaps/pre_backup_in_progress.png
enacrestic/pixmaps/repo_locked.png
enacrestic/pixmaps/unlock_in_progress.png
enacrestic-0.7.2.data/data/share/applications/enacrestic.desktop
enacrestic-0.7.2.data/data/share/icons/enacrestic.png
enacrestic-0.7.2.dist-info/LICENSE
enacrestic-0.7.2.dist-info/METADATA
enacrestic-0.7.2.dist-info/WHEEL
enacrestic-0.7.2.dist-info/entry_points.txt
enacrestic-0.7.2.dist-info/top_level.txt
enacrestic-0.7.2.dist-info/RECORD
