Metadata-Version: 2.1
Name: enacrestic
Version: 0.7.2
Summary: Automate backups using restic
Home-page: https://github.com/EPFL-ENAC/ENACrestic#readme
Author: Samuel Bancal
Author-email: Samuel.Bancal@epfl.ch
Project-URL: Bug Reports, https://github.com/EPFL-ENAC/ENACrestic/issues
Project-URL: Source, https://github.com/EPFL-ENAC/ENACrestic/
Keywords: backup,restic
Classifier: Programming Language :: Python :: 3
Classifier: Development Status :: 4 - Beta
Classifier: Environment :: X11 Applications :: Qt
Classifier: Intended Audience :: End Users/Desktop
Classifier: Intended Audience :: System Administrators
Classifier: License :: OSI Approved :: GNU General Public License v3 or later (GPLv3+)
Classifier: Operating System :: POSIX :: Linux
Classifier: Topic :: System :: Archiving :: Backup
Requires-Python: >=3.6, <4
License-File: LICENSE
Requires-Dist: PyQt5
Requires-Dist: python-pidfile
Requires-Dist: requests
Requires-Dist: dynaconf
Provides-Extra: dev
Provides-Extra: test
